<?xml version="1.0" encoding="utf-8"?>
<locale language="az" english-language-name="Azerbaijani">
   <info>
      <authorgroup>
         <author>
            <firstname>Mətin</firstname>
            <surname>Əmirov</surname>
            <affiliation>
               <address>
                  <email>amiroff@gmail.com</email>
               </address>
            </affiliation>
         </author>
      </authorgroup>
   </info>
   <mappings>
      <gentext key="above">Üstündə</gentext>
      <gentext key="Abstract">İcmal</gentext>
      <gentext key="abstract">İcmal</gentext>
      <gentext key="and">və</gentext>
      <gentext key="Answer">Cavab:</gentext>
      <gentext key="answer">Cavab:</gentext>
      <gentext key="Appendix">Əlavə</gentext>
      <gentext key="appendix">Əlavə</gentext>
      <gentext key="Article">Məqalə</gentext>
      <gentext key="article">Məqalə</gentext>
      <gentext key="Author">Müəllif</gentext>
      <gentext key="below">Altında</gentext>
      <gentext key="Bibliography">Qaynaqça</gentext>
      <gentext key="bibliography">Qaynaqça</gentext>
      <gentext key="Book">Kitab</gentext>
      <gentext key="book">Kitab</gentext>
      <gentext key="bullet">•</gentext>
      <gentext key="by"/>
      <gentext key="called">çağırıldı</gentext>
      <gentext key="CAUTION">DİQQƏT</gentext>
      <gentext key="Caution">Diqqət</gentext>
      <gentext key="caution">Diqqət</gentext>
      <gentext key="Chapter">Bölüm</gentext>
      <gentext key="chapter">Bölüm</gentext>
      <gentext key="Colophon">Kitab Haqqında</gentext>
      <gentext key="colophon">Kitab Haqqında</gentext>
      <gentext key="Copyright">Müəllif Hüququ</gentext>
      <gentext key="copyright">Müəllif Hüququ</gentext>
      <gentext key="Dedication">Həsr</gentext>
      <gentext key="dedication">Həsr</gentext>
      <gentext key="Draft">Şablon</gentext>
      <gentext key="Edited">Düzəldildi</gentext>
      <gentext key="edited">Düzəldildi</gentext>
      <gentext key="Editedby">Düzəliş edən</gentext>
      <gentext key="editedby">Düzəliş edən</gentext>
      <gentext key="Edition">Buraxılış</gentext>
      <gentext key="edition">Buraxılış</gentext>
      <gentext key="endquote">”</gentext>
      <gentext key="Equation">Tənlik</gentext>
      <gentext key="equation">Tənlik</gentext>
      <gentext key="Example">Nümunə</gentext>
      <gentext key="example">Nümunə</gentext>
      <gentext key="Figure">Fiqur</gentext>
      <gentext key="figure">Fiqur</gentext>
      <gentext key="Glossary">Lüğət</gentext>
      <gentext key="glossary">Lüğət</gentext>
      <gentext key="GlossSee">Bax</gentext>
      <gentext key="glosssee">Bax</gentext>
      <gentext key="GlossSeeAlso">Eləcə Də Bax</gentext>
      <gentext key="glossseealso">Eləcə Də Bax</gentext>
      <gentext key="IMPORTANT">VACİB</gentext>
      <gentext key="important">Vacib</gentext>
      <gentext key="Important">Vacib</gentext>
      <gentext key="in"/>
      <gentext key="Index">İndeks</gentext>
      <gentext key="index">İndeks</gentext>
      <gentext key="index symbols">Simvollar</gentext>
      <gentext key="ISBN">ISBN</gentext>
      <gentext key="isbn">ISBN</gentext>
      <gentext key="lastlistcomma">,</gentext>
      <gentext key="LegalNotice">Qanuni Qeyd</gentext>
      <gentext key="legalnotice">Qanuni Qeyd</gentext>
      <gentext key="listcomma">,</gentext>
      <gentext key="listofequations">Tənliklər</gentext>
      <gentext key="ListofEquations">Tənliklər</gentext>
      <gentext key="ListofExamples">Nümunələr</gentext>
      <gentext key="listofexamples">Nümunələr</gentext>
      <gentext key="ListofFigures">Fiqurlar</gentext>
      <gentext key="listoffigures">Fiqurlar</gentext>
      <gentext key="ListofProcedures">Üsullar</gentext>
      <gentext key="listofprocedures">Üsullar</gentext>
      <gentext key="listoftables">Cədvəllər</gentext>
      <gentext key="ListofTables">Cədvəllər</gentext>
      <gentext key="ListofUnknown">Naməlumlar</gentext>
      <gentext key="MsgAud">Hədəf Oxuyucu</gentext>
      <gentext key="msgaud">Hədəf Oxuyucu</gentext>
      <gentext key="MsgLevel">Səviyyə</gentext>
      <gentext key="msglevel">Səviyyə</gentext>
      <gentext key="MsgOrig">Mənbə</gentext>
      <gentext key="msgorig">Mənbə</gentext>
      <gentext key="nav-home">Ev</gentext>
      <gentext key="nav-next">Sonrakı</gentext>
      <gentext key="nav-next-sibling">İrəli</gentext>
      <gentext key="nav-prev">Əvvəlki</gentext>
      <gentext key="nav-prev-sibling">Geri</gentext>
      <gentext key="nav-toc">Məzmun</gentext>
      <gentext key="nav-up">Yuxarı</gentext>
      <gentext key="nestedendquote">’</gentext>
      <gentext key="nestedstartquote">‘</gentext>
      <gentext key="NOTE">QEYD</gentext>
      <gentext key="Note">Qeyd</gentext>
      <gentext key="note">Qeyd</gentext>
      <gentext key="notes">Qeydlər</gentext>
      <gentext key="Notes">Qeydlər</gentext>
      <gentext key="or">və ya</gentext>
      <gentext key="Part">Hissə</gentext>
      <gentext key="part">Hissə</gentext>
      <gentext key="Pgs">Shflr.</gentext>
      <gentext key="pgs">Shflr.</gentext>
      <gentext key="Preface">Önsöz</gentext>
      <gentext key="preface">Önsöz</gentext>
      <gentext key="Procedure">Üsul</gentext>
      <gentext key="procedure">Üsul</gentext>
      <gentext key="ProductionSet">Produksiya</gentext>
      <gentext key="PubDate">Yayimlama Tarixi</gentext>
      <gentext key="pubdate">Yayimlama Tarixi</gentext>
      <gentext key="Published">Yayimlama</gentext>
      <gentext key="published">Yayimlama</gentext>
      <gentext key="Qandadiv">S və C</gentext>
      <gentext key="qandadiv">S və C</gentext>
      <gentext key="Question">Sual:</gentext>
      <gentext key="question">Sual:</gentext>
      <gentext key="RefEntry"/>
      <gentext key="refentry"/>
      <gentext key="Reference">Xatırlatma</gentext>
      <gentext key="reference">Xatırlatma</gentext>
      <gentext key="RefName">Ad</gentext>
      <gentext key="refname">Ad</gentext>
      <gentext key="RefSection"/>
      <gentext key="refsection"/>
      <gentext key="RefSynopsisDiv">İcmal</gentext>
      <gentext key="refsynopsisdiv">İcmal</gentext>
      <gentext key="RevHistory">Nəzərdən Keçirmə Tarixçəsi</gentext>
      <gentext key="revhistory">Nəzərdən Keçirmə Tarixçəsi</gentext>
      <gentext key="Revisedby">Gözdən keçirən: </gentext>
      <gentext key="revisedby">Gözdən keçirən: </gentext>
      <gentext key="revision">Nəzərdən Keçirmə</gentext>
      <gentext key="Revision">Nəzərdən Keçirmə</gentext>
      <gentext key="sect1">Qisim</gentext>
      <gentext key="sect2">Qisim</gentext>
      <gentext key="sect3">Qisim</gentext>
      <gentext key="sect4">Qisim</gentext>
      <gentext key="sect5">Qisim</gentext>
      <gentext key="section">Qisim</gentext>
      <gentext key="Section">Qisim</gentext>
      <gentext key="sectioncalled"/>
      <gentext key="see">bax</gentext>
      <gentext key="See">Bax</gentext>
      <gentext key="seealso">eləcə də bax</gentext>
      <gentext key="Seealso">Eləcə Də Bax</gentext>
      <gentext key="SeeAlso">Eləcə Də Bax</gentext>
      <gentext key="set">Dəstə</gentext>
      <gentext key="Set">Dəstə</gentext>
      <gentext key="setindex">İndeksi Seç</gentext>
      <gentext key="SetIndex">İndeksi Seç</gentext>
      <gentext key="Sidebar"/>
      <gentext key="sidebar">Kənar Çubuğu</gentext>
      <gentext key="singleendquote">’</gentext>
      <gentext key="singlestartquote">‘</gentext>
      <gentext key="startquote">“</gentext>
      <gentext key="step">addım</gentext>
      <gentext key="Step">Addım</gentext>
      <gentext key="Table">Cədvəl</gentext>
      <gentext key="table">cədvəl</gentext>
      <gentext key="TableNotes">Qeydlər</gentext>
      <gentext key="tablenotes">Qeydlər</gentext>
      <gentext key="TableofContents">Məzmun</gentext>
      <gentext key="tableofcontents">Məzmun</gentext>
      <gentext key="the"/>
      <gentext key="tip">məsləhət</gentext>
      <gentext key="TIP">MƏSLƏHƏT</gentext>
      <gentext key="Tip">Məsləhət</gentext>
      <gentext key="unexpectedelementname">Gözlənməyən element adı</gentext>
      <gentext key="unsupported">dəstəklənmir</gentext>
      <gentext key="Warning">Xəbərdarlıq</gentext>
      <gentext key="warning">Xəbərdarlıq</gentext>
      <gentext key="WARNING">XƏBƏRDARLIQ</gentext>
      <gentext key="xrefto"/>
   </mappings>
   <properties name="language">
      <property name="writing-mode" value="lr-tb"/>
      <property name="hyphenation-character" value="-"/>
      <property name="hyphenation-push-character-count" value="2"/>
      <property name="hyphenation-remain-character-count" value="2"/>
   </properties>
   <properties name="number-format">
      <property name="part" value="I"/>
      <property name="reference" value="I"/>
      <property name="appendix" value="A"/>
      <property name="_default" value="1"/>
   </properties>
   <properties name="datetime">
      <property name="format" value="m/d/Y"/>
   </properties>
   <properties name="number-separator">
      <property name="_default" value="."/>
   </properties>
   <group name="refentry">
      <template name="refname-sep">, </template>
      <template name="refpurpose-sep"> — </template>
   </group>
   <group name="variablelist">
      <template name="sep">, </template>
      <template name="sep2">, </template>
      <template name="seplast">, </template>
   </group>
   <group name="refentry">
      <template name="refname-sep">, </template>
      <template name="refpurpose-sep"> — </template>
   </group>
   <group name="xlink">
      <template name="xlink-arclist-before"> [</template>
      <template name="xlink-arclist-after">] </template>
      <template name="xlink-arclist-titlesep">: </template>
      <template name="xlink-arclist-sep">, </template>
   </group>
   <property name="styles">
      <property name="person-name" value="first-last"/>
   </property>
   <group name="label">
      <template name="refname">{RefName}</template>
      <template name="see">{See} </template>
      <template name="seealso">{Seealso} </template>
      <template name="edited-by">{Editedby} </template>
   </group>
   <group name="label-separator">
      <template name="appendix">. </template>
      <template name="chapter">. </template>
      <template name="equation">. </template>
      <template name="example">. </template>
      <template name="figure">. </template>
      <template name="formalgroup">. </template>
      <template name="part">. </template>
      <template name="procedure">. </template>
      <template name="reference">. </template>
      <template name="table">. </template>
      <template name="_default"> </template>
   </group>
   <group name="title">
      <template name="abstract">%c</template>
      <template name="answer">%c</template>
      <template name="appendix">{Appendix} %l%.%c</template>
      <template name="article">%c</template>
      <template name="authorblurb">%c</template>
      <template name="bibliodiv">%c</template>
      <template name="biblioentry">%c</template>
      <template name="bibliography">%c</template>
      <template name="bibliolist">%c</template>
      <template name="bibliomixed">%c</template>
      <template name="bibliomset">%c</template>
      <template name="biblioset">%c</template>
      <template name="blockquote">%c</template>
      <template name="book">%c</template>
      <template name="calloutlist">%c</template>
      <template name="caution">%c</template>
      <template name="chapter">{Chapter} %l%.%c</template>
      <template name="colophon">%c</template>
      <template name="dedication">%c</template>
      <template name="equation">{Equation} %l%.%c</template>
      <template name="example">{Example} %l%.%c</template>
      <template name="figure">{Figure} %l%.%c</template>
      <template name="foil">%c</template>
      <template name="foilgroup">%c</template>
      <template name="formalpara">%c</template>
      <template name="glossary">%c</template>
      <template name="glossdiv">%c</template>
      <template name="glosslist">%c</template>
      <template name="glossentry">%c</template>
      <template name="important">%c</template>
      <template name="index">%c</template>
      <template name="indexdiv">%c</template>
      <template name="itemizedlist">%c</template>
      <template name="legalnotice">%c</template>
      <template name="listitem"/>
      <template name="lot">%c</template>
      <template name="msg">%c</template>
      <template name="msgexplan">%c</template>
      <template name="msgmain">%c</template>
      <template name="msgrel">%c</template>
      <template name="msgset">%c</template>
      <template name="msgsub">%c</template>
      <template name="note">%c</template>
      <template name="orderedlist">%c</template>
      <template name="part">{Part} %l%.%c</template>
      <template name="partintro">%c</template>
      <template name="preface">%c</template>
      <template name="procedure">%c</template>
      <template name="procedure.formal">{Procedure} %l%.%c</template>
      <template name="productionset">%c</template>
      <template name="productionset.formal">{ProductionSet} %l</template>
      <template name="qandadiv">%c</template>
      <template name="qandaentry">%c</template>
      <template name="qandaset">%c</template>
      <template name="question">%c</template>
      <template name="refentry">%c</template>
      <template name="reference">%c</template>
      <template name="refsection">%c</template>
      <template name="refsect1">%c</template>
      <template name="refsect2">%c</template>
      <template name="refsect3">%c</template>
      <template name="refsynopsisdiv">%c</template>
      <template name="refsynopsisdivinfo">%c</template>
      <template name="segmentedlist">%c</template>
      <template name="set">%c</template>
      <template name="setindex">%c</template>
      <template name="sidebar">%c</template>
      <template name="step">%c</template>
      <template name="table">{Table} %l%.%c</template>
      <template name="task">%c</template>
      <template name="tip">%c</template>
      <template name="toc">%c</template>
      <template name="variablelist">%c</template>
      <template name="varlistentry"/>
      <template name="warning">%c</template>
      <template name="TableofContents">{TableofContents}</template>
      <template name="ListofFigures">{ListofFigures}</template>
      <template name="ListofTables">{ListofTables}</template>
      <template name="ListofEquations">{ListofEquations}</template>
      <template name="ListofProcedures">{ListofProcedures}</template>
      <template name="ListofExamples">{ListofExamples}</template>
      <template name="ListofUnknown">{ListofUnknown}</template>
      <template name="_default">%c</template>
   </group>
   <group name="list-of-titles">
      <template name="article">%c</template>
      <template name="bibliography">%c</template>
      <template name="book">%c</template>
      <template name="dedication">%c</template>
      <template name="formalgroup">%l%.%c</template>
      <template name="forward">%c</template>
      <template name="glossary">%c</template>
      <template name="index">%c</template>
      <template name="preface">%c</template>
      <template name="setindex">%c</template>
      <template name="topic">%c</template>
      <template name="book/part">{Part} %l%.%c</template>
      <template name="book/reference">{Reference} %l%.%c</template>
      <template name="book/appendix">{Appendix} %l%.%c</template>
      <template name="book/chapter">{Chapter} %l%.%c</template>
      <template name="part/appendix">{Appendix} %l%.%c</template>
      <template name="part/chapter">{Chapter} %l%.%c</template>
      <template name="_default">%l%.%c</template>
   </group>
   <group name="title-unnumbered">
      <template name="_default">%c</template>
   </group>
   <group name="title-numbered">
      <template name="article/appendix">%l%.%c</template>
      <template name="appendix">{Appendix} %l%.%c</template>
      <template name="bridgehead">%l%.%c</template>
      <template name="chapter">{Chapter} %l%.%c</template>
      <template name="part">{Part} %l%.%c</template>
      <template name="sect1">%l%.%c</template>
      <template name="sect2">%l%.%c</template>
      <template name="sect3">%l%.%c</template>
      <template name="sect4">%l%.%c</template>
      <template name="sect5">%l%.%c</template>
      <template name="section">%l%.%c</template>
      <template name="simplesect">%c</template>
      <template name="refsect1">%c</template>
      <template name="refsect2">%c</template>
      <template name="refsect3">%c</template>
      <template name="refsection">%c</template>
      <template name="_default">%l%.%c</template>
   </group>
   <group name="subfigure-title">
      <template name="figure">{subfigure} %l%.%c</template>
      <template name="table">{subtable} %l%.%c</template>
      <template name="equation">{subequation} %l%.%c</template>
      <template name="example">{subexample} %l%.%c</template>
   </group>
   <group name="title-generated">
      <template name="abstract">{Abstract}</template>
      <template name="acknowledgements">{Acknowledgements}</template>
      <template name="bibliography">{Bibliography}</template>
      <template name="caution">{Caution}</template>
      <template name="danger">{Danger}</template>
      <template name="dedication">{Dedication}</template>
      <template name="glossary">{Glossary}</template>
      <template name="important">{Important}</template>
      <template name="index">{Index}</template>
      <template name="legalnotice">{LegalNotice}</template>
      <template name="note">{Note}</template>
      <template name="revhistory">{RevHistory}</template>
      <template name="setindex">{SetIndex}</template>
      <template name="tip">{Tip}</template>
      <template name="warning">{Warning}</template>
   </group>
   <group name="xref">
      <template name="abstract">%c</template>
      <template name="answer">{Answer} %l</template>
      <template name="appendix">%c</template>
      <template name="article">%c</template>
      <template name="authorblurb">%c</template>
      <template name="bibliodiv">%c</template>
      <template name="bibliography">%c</template>
      <template name="bibliomset">%c</template>
      <template name="biblioset">%c</template>
      <template name="blockquote">%c</template>
      <template name="book">%c</template>
      <template name="calloutlist">%c</template>
      <template name="caution">%c</template>
      <template name="chapter">%c</template>
      <template name="colophon">%c</template>
      <template name="constraintdef">%c</template>
      <template name="dedication">%c</template>
      <template name="equation">%c</template>
      <template name="example">%c</template>
      <template name="figure">%c</template>
      <template name="foil">%c</template>
      <template name="foilgroup">%c</template>
      <template name="formalpara">%c</template>
      <template name="glossary">%c</template>
      <template name="glossdiv">%c</template>
      <template name="important">%c</template>
      <template name="index">%c</template>
      <template name="indexdiv">%c</template>
      <template name="itemizedlist">%c</template>
      <template name="legalnotice">%c</template>
      <template name="lot">%c</template>
      <template name="msg">%c</template>
      <template name="msgexplan">%c</template>
      <template name="msgmain">%c</template>
      <template name="msgrel">%c</template>
      <template name="msgset">%c</template>
      <template name="msgsub">%c</template>
      <template name="note">%c</template>
      <template name="orderedlist">%c</template>
      <template name="part">%c</template>
      <template name="partintro">%c</template>
      <template name="preface">%c</template>
      <template name="procedure">%c</template>
      <template name="productionset">%c</template>
      <template name="qandadiv">%c</template>
      <template name="qandaentry">{Question} %l</template>
      <template name="qandaset">%c</template>
      <template name="question">{Question} %l</template>
      <template name="reference">%c</template>
      <template name="refsynopsisdiv">%c</template>
      <template name="segmentedlist">%c</template>
      <template name="set">%c</template>
      <template name="setindex">%c</template>
      <template name="sidebar">%c</template>
      <template name="table">%c</template>
      <template name="tip">%c</template>
      <template name="toc">%c</template>
      <template name="variablelist">%c</template>
      <template name="warning">%c</template>
      <template name="olink.document.citation"> in %o</template>
      <template name="olink.page.citation"> (page %p)</template>
      <template name="page.citation"> [%p]</template>
      <template name="page">(page %p)</template>
      <template name="docname"> in %o</template>
      <template name="docnamelong"> in the document titled %o</template>
      <template name="pageabbrev">(p%.%p)</template>
      <template name="Page">Page %p</template>
      <template name="bridgehead">{sectioncalled} {startquote}%c{endquote}</template>
      <template name="refsection">{sectioncalled} {startquote}%c{endquote}</template>
      <template name="refsect1">{sectioncalled} {startquote}%c{endquote}</template>
      <template name="refsect2">{sectioncalled} {startquote}%c{endquote}</template>
      <template name="refsect3">{sectioncalled} {startquote}%c{endquote}</template>
      <template name="sect1">{sectioncalled} {startquote}%c{endquote}</template>
      <template name="sect2">{sectioncalled} {startquote}%c{endquote}</template>
      <template name="sect3">{sectioncalled} {startquote}%c{endquote}</template>
      <template name="sect4">{sectioncalled} {startquote}%c{endquote}</template>
      <template name="sect5">{sectioncalled} {startquote}%c{endquote}</template>
      <template name="section">{sectioncalled} {startquote}%c{endquote}</template>
      <template name="simplesect">{sectioncalled} {startquote}%c{endquote}</template>
      <template name="step">{step} %l</template>
      <template name="refnamediv">%c</template>
      <template name="_default">%l</template>
   </group>
   <group name="xref-number">
      <template name="answer">{Answer} %l</template>
      <template name="appendix">{Appendix} %l</template>
      <template name="bridgehead">{Section} %l</template>
      <template name="chapter">{Chapter} %l</template>
      <template name="equation">{Equation} %l</template>
      <template name="example">{Example} %l</template>
      <template name="figure">{Figure} %l</template>
      <template name="part">{Part} %l</template>
      <template name="procedure">{Procedure} %l</template>
      <template name="productionset">{ProductionSet} %l</template>
      <template name="qandadiv">{Qandadiv} %l</template>
      <template name="qandaentry">{Question} %l</template>
      <template name="question">{Question} %l</template>
      <template name="sect1">{Section} %l</template>
      <template name="sect2">{Section} %l</template>
      <template name="sect3">{Section} %l</template>
      <template name="sect4">{Section} %l</template>
      <template name="sect5">{Section} %l</template>
      <template name="section">{Section} %l</template>
      <template name="table">{Table} %l</template>
   </group>
   <group name="xref-number-and-title">
      <template name="appendix">{Appendix} %l, %c</template>
      <template name="bridgehead">{Section} %l, {startquote}%c{endquote}</template>
      <template name="chapter">{Chapter} %l, %c</template>
      <template name="equation">{Equation} %l, {startquote}%c{endquote}</template>
      <template name="example">{Example} %l, {startquote}%c{endquote}</template>
      <template name="figure">{Figure} %l, {startquote}%c{endquote}</template>
      <template name="part">{Part} %l, {startquote}%c{endquote}</template>
      <template name="procedure">{Procedure} %l, {startquote}%c{endquote}</template>
      <template name="productionset">{ProductionSet} %l, {startquote}%c{endquote}</template>
      <template name="qandadiv">{Qandadiv} %l, {startquote}%c{endquote}</template>
      <template name="refsect1">{sectioncalled} {startquote}%c{endquote}</template>
      <template name="refsect2">{sectioncalled} {startquote}%c{endquote}</template>
      <template name="refsect3">{sectioncalled} {startquote}%c{endquote}</template>
      <template name="refsection">{sectioncalled} {startquote}%c{endquote}</template>
      <template name="sect1">{Section} %l, {startquote}%c{endquote}</template>
      <template name="sect2">{Section} %l, {startquote}%c{endquote}</template>
      <template name="sect3">{Section} %l, {startquote}%c{endquote}</template>
      <template name="sect4">{Section} %l, {startquote}%c{endquote}</template>
      <template name="sect5">{Section} %l, {startquote}%c{endquote}</template>
      <template name="section">{Section} %l, {startquote}%c{endquote}</template>
      <template name="simplesect">{sectioncalled} {startquote}%c{endquote}</template>
      <template name="table">{Table} %l, {startquote}%c{endquote}</template>
      <template name="_default">%l%.%c</template>
   </group>
   <group name="authorgroup">
      <template name="sep">{listcomma} </template>
      <template name="sep2"> {and} </template>
      <template name="seplast">{lastlistcomma} {and} </template>
   </group>
   <list name="index-seealso">
      <items>({seealso} %c)</items>
      <items>({seealso} %c<repeat>, %c</repeat>)</items>
   </list>
   <list name="index-seeie">
      <items>({see} %c)</items>
      <items>({see} %c<repeat>, %c</repeat>)</items>
   </list>
   <list name="index-seealsoie">
      <items>({seealso} %c)</items>
      <items>({seealso} %c<repeat>, %c</repeat>)</items>
   </list>
   <list name="glossary-seealso">
      <items>{Seealso} %c.</items>
      <items>{Seealso} %c<repeat>, %c</repeat>.</items>
   </list>
   <list name="varlistentry">
      <items>%c</items>
      <items>%c<repeat>, %c</repeat>
      </items>
   </list>
   <list name="_default">
      <items>%c</items>
      <items>%c {and} %c</items>
      <items>%c<repeat>, %c</repeat>, {and} %c</items>
   </list>
   <group name="glossary">
      <template name="see">{GlossSee} %c.</template>
      <template name="seealso">{GlossSeeAlso} %c.</template>
      <template name="seealso-separator">, </template>
      <template name="glossterm-separator">, </template>
   </group>
   <group name="index"/>
   <group name="msgset">
      <template name="msgaud">{msgaud}: </template>
      <template name="msglevel">{msglevel}: </template>
      <template name="msgorig">{msgorig}: </template>
   </group>
   <group name="termdef">
      <template name="prefix">[Definition: </template>
      <template name="suffix">]</template>
   </group>
   <group name="datetime-full">
      <template name="January">Janvar</template>
      <template name="February">Fevral</template>
      <template name="March">Mart</template>
      <template name="April">Aprel</template>
      <template name="May">May</template>
      <template name="June">İyun</template>
      <template name="July">İyul</template>
      <template name="August">Avqust</template>
      <template name="September">Sentyabr</template>
      <template name="October">Oktyabr</template>
      <template name="November">Noyabr</template>
      <template name="December">Dekabr</template>
      <template name="Monday">Bazar Ertəsi</template>
      <template name="Tuesday">Çərşənbə Axşamı </template>
      <template name="Wednesday">Çərşənbə</template>
      <template name="Thursday">Cümə Axşamı</template>
      <template name="Friday">Cümə</template>
      <template name="Saturday">Şənbə</template>
      <template name="Sunday">Bazar</template>
   </group>
   <group name="datetime-abbrev">
      <template name="Jan">Yan</template>
      <template name="Feb">Fev</template>
      <template name="Mar">Mar</template>
      <template name="Apr">Apr</template>
      <template name="May">May</template>
      <template name="Jun">İyn</template>
      <template name="Jul">İyl</template>
      <template name="Aug">Avq</template>
      <template name="Sep">Sen</template>
      <template name="Oct">Okt</template>
      <template name="Nov">Noy</template>
      <template name="Dec">Dek</template>
      <template name="Mon">Ber</template>
      <template name="Tue">Çax</template>
      <template name="Wed">Çər</template>
      <template name="Thu">Cax</template>
      <template name="Fri">Cüm</template>
      <template name="Sat">Şnb</template>
      <template name="Sun">Baz</template>
   </group>
   <letters>
      <l i="-1"/>
      <l i="0">İşarələr</l>
      <l i="1">A</l>
      <l i="1">a</l>
      <l i="2">B</l>
      <l i="2">b</l>
      <l i="3">C</l>
      <l i="3">c</l>
      <l i="4">Ç</l>
      <l i="5">ç</l>
      <l i="5">D</l>
      <l i="5">d</l>
      <l i="6">E</l>
      <l i="6">e</l>
      <l i="7">e</l>
      <l i="7">e</l>
      <l i="8">Ə</l>
      <l i="8">ə</l>
      <l i="9">G</l>
      <l i="9">g</l>
      <l i="10">Ğ</l>
      <l i="10">ğ</l>
      <l i="11">H</l>
      <l i="11">h</l>
      <l i="12">X</l>
      <l i="12">x</l>
      <l i="13">I</l>
      <l i="13">ı</l>
      <l i="14">İ</l>
      <l i="14">i</l>
      <l i="15">J</l>
      <l i="15">j</l>
      <l i="16">K</l>
      <l i="16">k</l>
      <l i="17">Q</l>
      <l i="17">q</l>
      <l i="18">L</l>
      <l i="18">l</l>
      <l i="19">M</l>
      <l i="19">m</l>
      <l i="20">N</l>
      <l i="20">n</l>
      <l i="21">O</l>
      <l i="21">o</l>
      <l i="22">Ö</l>
      <l i="22">ö</l>
      <l i="23">P</l>
      <l i="23">p</l>
      <l i="24">R</l>
      <l i="24">r</l>
      <l i="25">S</l>
      <l i="25">s</l>
      <l i="26">Ş</l>
      <l i="26">ş</l>
      <l i="27">T</l>
      <l i="27">t</l>
      <l i="28">U</l>
      <l i="28">u</l>
      <l i="29">Ü</l>
      <l i="29">ü</l>
      <l i="30">V</l>
      <l i="30">v</l>
      <l i="31">Y</l>
      <l i="31">y</l>
      <l i="32">Z</l>
      <l i="32">z</l>
   </letters>
</locale>
