<?xml version="1.0" encoding="utf-8"?>
<locale xmlns="http://docbook.org/ns/docbook/l10n/source"
         xmlns:db="http://docbook.org/ns/docbook"
         language="it"
         english-language-name="Italian">
   <info>
      <authorgroup>
         <author>
            <firstname>Federico</firstname>
            <surname>De Faveri</surname>
            <affiliation>
               <address>
                  <email>defaveri@di.unipi.it</email>
               </address>
            </affiliation>
         </author>
         <author>
            <firstname>Andrea</firstname>
            <surname>Rizzi</surname>
            <affiliation>
               <address>
                  <email>a.rizzi@sns.it</email>
               </address>
            </affiliation>
         </author>
         <author>
            <firstname>Alex</firstname>
            <surname>Dupre</surname>
            <affiliation>
               <address>
                  <email>sysadmin@alexdupre.com</email>
               </address>
            </affiliation>
         </author>
         <author>
            <firstname>Federico</firstname>
            <surname>Zenith</surname>
            <affiliation>
               <address>
                  <email>zenith@chemeng.ntnu.no</email>
               </address>
            </affiliation>
         </author>
      </authorgroup>
   </info>
   <mappings>
      <gentext key="above">sopra</gentext>
      <gentext key="Abstract">Sommario</gentext>
      <gentext key="abstract">Sommario</gentext>
      <gentext key="and">e</gentext>
      <gentext key="Answer">Risposta:</gentext>
      <gentext key="answer">Risposta:</gentext>
      <gentext key="Appendix">Appendice</gentext>
      <gentext key="appendix">Appendice</gentext>
      <gentext key="Article">Articolo</gentext>
      <gentext key="article">Articolo</gentext>
      <gentext key="Author">Autore</gentext>
      <gentext key="Authors">Autori</gentext>
      <gentext key="below">sotto</gentext>
      <gentext key="Bibliography">Bibliografia</gentext>
      <gentext key="bibliography">Bibliografia</gentext>
      <gentext key="Book">Libro</gentext>
      <gentext key="book">Libro</gentext>
      <gentext key="bullet">•</gentext>
      <gentext key="by">di</gentext>
      <gentext key="CAUTION">ATTENZIONE</gentext>
      <gentext key="Caution">Attenzione</gentext>
      <gentext key="caution">Attenzione</gentext>
      <gentext key="Chapter">Capitolo</gentext>
      <gentext key="chapter">Capitolo</gentext>
      <gentext key="Colophon">Colofone</gentext>
      <gentext key="colophon">Colofone</gentext>
      <gentext key="copyeditor">Correttore di bozze</gentext>
      <gentext key="Copyright">Diritto d'autore</gentext>
      <gentext key="copyright">Diritto d'autore</gentext>
      <gentext key="Dedication">Dedica</gentext>
      <gentext key="dedication">Dedica</gentext>
      <gentext key="Draft">Bozza</gentext>
      <gentext key="Edited">A cura</gentext>
      <gentext key="edited">A cura</gentext>
      <gentext key="Editedby">A cura di</gentext>
      <gentext key="editedby">A cura di</gentext>
      <gentext key="Edition">Edizione</gentext>
      <gentext key="edition">Edizione</gentext>
      <gentext key="Editor">Editor</gentext>
      <gentext key="endquote">»</gentext>
      <gentext key="Equation">Equazione</gentext>
      <gentext key="equation">Equazione</gentext>
      <gentext key="Example">Esempio</gentext>
      <gentext key="example">Esempio</gentext>
      <gentext key="Figure">Figura</gentext>
      <gentext key="figure">Figura</gentext>
      <gentext key="Glossary">Glossario</gentext>
      <gentext key="glossary">Glossario</gentext>
      <gentext key="GlossSee">Vedi</gentext>
      <gentext key="glosssee">Vedi</gentext>
      <gentext key="GlossSeeAlso">Vedi anche</gentext>
      <gentext key="glossseealso">Vedi anche</gentext>
      <gentext key="graphicdesigner">Progettista grafico</gentext>
      <gentext key="hyphenation-character">-</gentext>
      <gentext key="hyphenation-push-character-count">2</gentext>
      <gentext key="hyphenation-remain-character-count">2</gentext>
      <gentext key="IMPORTANT">IMPORTANTE</gentext>
      <gentext key="important">Importante</gentext>
      <gentext key="Important">Importante</gentext>
      <gentext key="in">in</gentext>
      <gentext key="Index">Indice analitico</gentext>
      <gentext key="index">Indice analitico</gentext>
      <gentext key="index symbols">Simboli</gentext>
      <gentext key="ISBN">ISBN</gentext>
      <gentext key="isbn">ISBN</gentext>
      <gentext key="lastlistcomma">,</gentext>
      <gentext key="LegalNotice">Nota Legale</gentext>
      <gentext key="legalnotice">Nota Legale</gentext>
      <gentext key="listcomma">,</gentext>
      <gentext key="listofequations">Lista delle equazioni</gentext>
      <gentext key="ListofEquations">Lista delle equazioni</gentext>
      <gentext key="ListofExamples">Lista degli esempi</gentext>
      <gentext key="listofexamples">Lista degli esempi</gentext>
      <gentext key="ListofFigures">Lista delle figure</gentext>
      <gentext key="listoffigures">Lista delle figure</gentext>
      <gentext key="ListofProcedures">Lista delle procedure</gentext>
      <gentext key="listofprocedures">Lista delle procedure</gentext>
      <gentext key="listoftables">Lista delle tabelle</gentext>
      <gentext key="ListofTables">Lista delle tabelle</gentext>
      <gentext key="ListofUnknown">Lista degli sconosciuti</gentext>
      <gentext key="listofunknown">Lista degli sconosciuti</gentext>
      <gentext key="MsgAud">Pubblico</gentext>
      <gentext key="msgaud">Pubblico</gentext>
      <gentext key="MsgLevel">Livello</gentext>
      <gentext key="msglevel">Livello</gentext>
      <gentext key="MsgOrig">Origine</gentext>
      <gentext key="msgorig">Origine</gentext>
      <gentext key="nav-home">Partenza</gentext>
      <gentext key="nav-next">Avanti</gentext>
      <gentext key="nav-next-sibling">Salta Avanti</gentext>
      <gentext key="nav-prev">Indietro</gentext>
      <gentext key="nav-prev-sibling">Salta Indietro</gentext>
      <gentext key="nav-toc">Sommario</gentext>
      <gentext key="nav-up">Risali</gentext>
      <gentext key="nestedendquote">”</gentext>
      <gentext key="nestedstartquote">“</gentext>
      <gentext key="NOTE">NOTA</gentext>
      <gentext key="Note">Nota</gentext>
      <gentext key="note">Nota</gentext>
      <gentext key="notes">Note</gentext>
      <gentext key="Notes">Note</gentext>
      <gentext key="or">o</gentext>
      <gentext key="Part">Parte</gentext>
      <gentext key="part">Parte</gentext>
      <gentext key="Pgs">pp.</gentext>
      <gentext key="pgs">pp.</gentext>
      <gentext key="Preface">Prefazione</gentext>
      <gentext key="preface">Prefazione</gentext>
      <gentext key="Procedure">Procedura</gentext>
      <gentext key="procedure">Procedura</gentext>
      <gentext key="productioneditor">Montatore</gentext>
      <gentext key="ProductionSet">Produzione</gentext>
      <gentext key="PubDate">Data di pubblicazione</gentext>
      <gentext key="pubdate">Data di pubblicazione</gentext>
      <gentext key="Published">Pubblicato</gentext>
      <gentext key="published">Pubblicato</gentext>
      <gentext key="Publisher">Editore</gentext>
      <gentext key="Qandadiv">Domande e risposte</gentext>
      <gentext key="qandadiv">Domande e risposte</gentext>
      <gentext key="QandASet">Domande ricorrenti</gentext>
      <gentext key="Question">Domanda:</gentext>
      <gentext key="question">Domanda:</gentext>
      <gentext key="RefEntry"/>
      <gentext key="refentry"/>
      <gentext key="Reference">Riferimento</gentext>
      <gentext key="reference">Riferimento</gentext>
      <gentext key="References">Riferimenti</gentext>
      <gentext key="RefName">Nome</gentext>
      <gentext key="refname">Nome</gentext>
      <gentext key="RefSection"/>
      <gentext key="refsection"/>
      <gentext key="RefSynopsisDiv">Sinossi</gentext>
      <gentext key="refsynopsisdiv">Sinossi</gentext>
      <gentext key="RevHistory">Diario delle Revisioni</gentext>
      <gentext key="revhistory">Diario delle Revisioni</gentext>
      <gentext key="Revisedby">Revisionato da: </gentext>
      <gentext key="revisedby">Revisionato da: </gentext>
      <gentext key="revision">Revisione</gentext>
      <gentext key="Revision">Revisione</gentext>
      <gentext key="sect1">Sezione</gentext>
      <gentext key="sect2">Sezione</gentext>
      <gentext key="sect3">Sezione</gentext>
      <gentext key="sect4">Sezione</gentext>
      <gentext key="sect5">Sezione</gentext>
      <gentext key="section">Sezione</gentext>
      <gentext key="Section">Sezione</gentext>
      <gentext key="sectioncalled">sezione chiamata</gentext>
      <gentext key="see">vedi</gentext>
      <gentext key="See">Vedi</gentext>
      <gentext key="seealso">vedi anche</gentext>
      <gentext key="Seealso">Vedi anche</gentext>
      <gentext key="SeeAlso">Vedi Anche</gentext>
      <gentext key="set">Raccolta</gentext>
      <gentext key="Set">Raccolta</gentext>
      <gentext key="setindex">Indice della raccolta</gentext>
      <gentext key="SetIndex">Indice della raccolta</gentext>
      <gentext key="Sidebar"/>
      <gentext key="sidebar">nota a margine</gentext>
      <gentext key="singleendquote">’</gentext>
      <gentext key="singlestartquote">‘</gentext>
      <gentext key="startquote">«</gentext>
      <gentext key="step">passo</gentext>
      <gentext key="Step">Passo</gentext>
      <gentext key="Table">Tabella</gentext>
      <gentext key="table">Tabella</gentext>
      <gentext key="TableNotes">Note</gentext>
      <gentext key="tablenotes">Note</gentext>
      <gentext key="TableofContents">Indice</gentext>
      <gentext key="tableofcontents">Indice</gentext>
      <gentext key="task">Attività</gentext>
      <gentext key="Task">Attività</gentext>
      <gentext key="technicaleditor">Revisore tecnico</gentext>
      <gentext key="tip">Suggerimento</gentext>
      <gentext key="TIP">SUGGERIMENTO</gentext>
      <gentext key="Tip">Suggerimento</gentext>
      <gentext key="translator">Traduttore</gentext>
      <gentext key="unexpectedelementname">Nome di elemento inatteso</gentext>
      <gentext key="unsupported">non supportato</gentext>
      <gentext key="Warning">Avvertimento</gentext>
      <gentext key="warning">avvertimento</gentext>
      <gentext key="WARNING">AVVERTIMENTO</gentext>
      <gentext key="writing-mode">lr-tb</gentext>
      <gentext key="xrefto">riferimento a</gentext>
      <gentext key="iso690.lastfirst.sep">, </gentext>
      <gentext key="iso690.alt.person.two.sep"> – </gentext>
      <gentext key="iso690.alt.person.last.sep"> – </gentext>
      <gentext key="iso690.alt.person.more.sep"> – </gentext>
      <gentext key="iso690.primary.editor"> (ed.)</gentext>
      <gentext key="iso690.primary.many">, et al.</gentext>
      <gentext key="iso690.primary.sep">. </gentext>
      <gentext key="iso690.submaintitle.sep">: </gentext>
      <gentext key="iso690.title.sep">. </gentext>
      <gentext key="iso690.othertitle.sep">, </gentext>
      <gentext key="iso690.medium1"> [</gentext>
      <gentext key="iso690.medium2">]</gentext>
      <gentext key="iso690.secondary.person.sep">; </gentext>
      <gentext key="iso690.secondary.sep">. </gentext>
      <gentext key="iso690.respons.sep">. </gentext>
      <gentext key="iso690.edition.sep">. </gentext>
      <gentext key="iso690.edition.serial.sep">, </gentext>
      <gentext key="iso690.issuing.range">-</gentext>
      <gentext key="iso690.issuing.div">, </gentext>
      <gentext key="iso690.issuing.sep">. </gentext>
      <gentext key="iso690.partnr.sep">. </gentext>
      <gentext key="iso690.placepubl.sep">: </gentext>
      <gentext key="iso690.publyear.sep">, </gentext>
      <gentext key="iso690.pubinfo.sep">. </gentext>
      <gentext key="iso690.spec.pubinfo.sep">, </gentext>
      <gentext key="iso690.upd.sep">, </gentext>
      <gentext key="iso690.datecit1"> [cit.: </gentext>
      <gentext key="iso690.datecit2">]</gentext>
      <gentext key="iso690.extent.sep">. </gentext>
      <gentext key="iso690.locs.sep">, </gentext>
      <gentext key="iso690.location.sep">. </gentext>
      <gentext key="iso690.serie.sep">. </gentext>
      <gentext key="iso690.notice.sep">. </gentext>
      <gentext key="iso690.access">Disponibile </gentext>
      <gentext key="iso690.acctoo">Disponibile anche </gentext>
      <gentext key="iso690.onwww">sul Web</gentext>
      <gentext key="iso690.oninet">su Internet</gentext>
      <gentext key="iso690.access.end">: </gentext>
      <gentext key="iso690.link1">&lt;</gentext>
      <gentext key="iso690.link2">&gt;</gentext>
      <gentext key="iso690.access.sep">. </gentext>
      <gentext key="iso690.isbn">ISBN </gentext>
      <gentext key="iso690.issn">ISSN </gentext>
      <gentext key="iso690.stdnum.sep">. </gentext>
      <gentext key="iso690.patcountry.sep">. </gentext>
      <gentext key="iso690.pattype.sep">, </gentext>
      <gentext key="iso690.patnum.sep">. </gentext>
      <gentext key="iso690.patdate.sep">. </gentext>
   </mappings>
   <group name="number-format">
      <template match="self::db:part">I</template>
      <template match="self::db:reference">I</template>
      <template match="self::db:appendix">A</template>
      <template match="true()">1</template>
   </group>
   <group name="date-format">
      <template match="true()">[D01]/[M01]/[Y0001]</template>
   </group>
   <group name="datetime-format">
      <template match="true()">[D01]/[M01]/[Y0001]</template>
   </group>
   <group name="number-separator">
      <template match="true()">.</template>
   </group>
   <group name="keycap"/>
   <group name="name-style">
      <template match="self::db:personname">first-last</template>
   </group>
   <group name="label">
      <template match="self::db:refnamediv">{RefName}</template>
      <template match="self::db:refname">{RefName}</template>
      <template match="self::db:see">{See}</template>
      <template match="self::db:seealso">{Seealso}</template>
      <template match="self::db:editor">{Editedby}</template>
      <template match="self::db:msgaud">{msgaud}</template>
      <template match="self::db:msglevel">{msglevel}</template>
      <template match="self::db:msgorig">{msgorig}</template>
   </group>
   <group name="label-separator">
      <template match="self::db:msgaud">: </template>
      <template match="self::db:msglevel">: </template>
      <template match="self::db:msgorig">: </template>
      <template match="self::db:editor"> </template>
      <template match="self::db:see"> </template>
      <template match="self::db:seealso"> </template>
      <template match="true()">. </template>
   </group>
   <group name="separator">
      <template match="true()">, </template>
   </group>
   <group name="table-of-contents">
      <template match="true()">{TableofContents}</template>
   </group>
   <group name="list-of-figures">
      <template match="true()">{ListofFigures}</template>
   </group>
   <group name="list-of-tables">
      <template match="true()">{ListofTables}</template>
   </group>
   <group name="list-of-equations">
      <template match="true()">{ListofEquations}</template>
   </group>
   <group name="list-of-procedures">
      <template match="true()">{ListofProcedures}</template>
   </group>
   <group name="list-of-examples">
      <template match="true()">{ListofExamples}</template>
   </group>
   <group name="list-of-unknown">
      <template match="true()">{ListofUnknown}</template>
   </group>
   <group name="list-of-titles">
      <template match="self::db:part[parent::db:book]">{Part} %l%.%c</template>
      <template match="self::db:reference[parent::db:book]">{Reference} %l%.%c</template>
      <template match="self::db:section[ancestor::db:preface]">%c</template>
      <template match="self::db:sect1[ancestor::db:preface]">%c</template>
      <template match="self::db:sect2[ancestor::db:preface]">%c</template>
      <template match="self::db:sect3[ancestor::db:preface]">%c</template>
      <template match="self::db:sect4[ancestor::db:preface]">%c</template>
      <template match="self::db:sect5[ancestor::db:preface]">%c</template>
      <template match="self::db:acknowledgements">%c</template>
      <template match="self::db:article">%c</template>
      <template match="self::db:bibliography">%c</template>
      <template match="self::db:book">%c</template>
      <template match="self::db:set">%c</template>
      <template match="self::db:colophon">%c</template>
      <template match="self::db:dedication">%c</template>
      <template match="self::db:formalgroup">%l%.%c</template>
      <template match="self::db:forward">%c</template>
      <template match="self::db:glossary">%c</template>
      <template match="self::db:index">%c</template>
      <template match="self::db:preface">%c</template>
      <template match="self::db:setindex">%c</template>
      <template match="self::db:topic">%c</template>
      <template match="true()">%l%.%c</template>
   </group>
   <group name="title-unnumbered">
      <template match="self::db:abstract">%c</template>
      <template match="self::db:answer">%c</template>
      <template match="self::db:article">%c</template>
      <template match="self::db:authorblurb">%c</template>
      <template match="self::db:bibliodiv">%c</template>
      <template match="self::db:biblioentry">%c</template>
      <template match="self::db:bibliography">%c</template>
      <template match="self::db:bibliolist">%c</template>
      <template match="self::db:bibliomixed">%c</template>
      <template match="self::db:bibliomset">%c</template>
      <template match="self::db:biblioset">%c</template>
      <template match="self::db:blockquote">%c</template>
      <template match="self::db:book">%c</template>
      <template match="self::db:calloutlist">%c</template>
      <template match="self::db:caution">%c</template>
      <template match="self::db:colophon">%c</template>
      <template match="self::db:dedication">%c</template>
      <template match="self::db:equation">{Equation} %l%.%c</template>
      <template match="self::db:example">{Example} %l%.%c</template>
      <template match="self::db:figure">{Figure} %l%.%c</template>
      <template match="self::db:foil">%c</template>
      <template match="self::db:foilgroup">%c</template>
      <template match="self::db:formalpara">%c</template>
      <template match="self::db:glossary">%c</template>
      <template match="self::db:glossdiv">%c</template>
      <template match="self::db:glosslist">%c</template>
      <template match="self::db:glossentry">%c</template>
      <template match="self::db:important">%c</template>
      <template match="self::db:index">%c</template>
      <template match="self::db:indexdiv">%c</template>
      <template match="self::db:itemizedlist">%c</template>
      <template match="self::db:legalnotice">%c</template>
      <template match="self::db:listitem"/>
      <template match="self::db:lot">%c</template>
      <template match="self::db:msg">%c</template>
      <template match="self::db:msgexplan">%c</template>
      <template match="self::db:msgmain">%c</template>
      <template match="self::db:msgrel">%c</template>
      <template match="self::db:msgset">%c</template>
      <template match="self::db:msgsub">%c</template>
      <template match="self::db:note">%c</template>
      <template match="self::db:orderedlist">%c</template>
      <template match="self::db:partintro">%c</template>
      <template match="self::db:preface">%c</template>
      <template match="self::db:procedure">{Procedure} %l%.%c</template>
      <template match="self::db:productionset">%c</template>
      <template match="self::db:productionset.formal">{ProductionSet} %l</template>
      <template match="self::db:qandadiv">%c</template>
      <template match="self::db:qandaentry">%c</template>
      <template match="self::db:qandaset">%c</template>
      <template match="self::db:question">%c</template>
      <template match="self::db:refentry">%c</template>
      <template match="self::db:reference">%c</template>
      <template match="self::db:refsection">%c</template>
      <template match="self::db:refsect1">%c</template>
      <template match="self::db:refsect2">%c</template>
      <template match="self::db:refsect3">%c</template>
      <template match="self::db:refsynopsisdiv">%c</template>
      <template match="self::db:refsynopsisdivinfo">%c</template>
      <template match="self::db:segmentedlist">%c</template>
      <template match="self::db:set">%c</template>
      <template match="self::db:setindex">%c</template>
      <template match="self::db:sidebar">%c</template>
      <template match="self::db:step">%c</template>
      <template match="self::db:table">{Table} %l%.%c</template>
      <template match="self::db:task">%c</template>
      <template match="self::db:tasksummary">%c</template>
      <template match="self::db:taskprerequisites">%c</template>
      <template match="self::db:taskrelated">%c</template>
      <template match="self::db:tip">%c</template>
      <template match="self::db:toc">%c</template>
      <template match="self::db:variablelist">%c</template>
      <template match="self::db:varlistentry"/>
      <template match="self::db:warning">%c</template>
      <template match="true()">%c</template>
   </group>
   <group name="title-numbered">
      <template match="self::db:section[ancestor::db:preface]">%c</template>
      <template match="self::db:sect1[ancestor::db:preface]">%c</template>
      <template match="self::db:sect2[ancestor::db:preface]">%c</template>
      <template match="self::db:sect3[ancestor::db:preface]">%c</template>
      <template match="self::db:sect4[ancestor::db:preface]">%c</template>
      <template match="self::db:sect5[ancestor::db:preface]">%c</template>
      <template match="self::db:appendix[parent::db:article]">%l%.%c</template>
      <template match="self::db:appendix">{Appendix} %l%.%c</template>
      <template match="self::db:bridgehead">%l%.%c</template>
      <template match="self::db:chapter">{Chapter} %l%.%c</template>
      <template match="self::db:part">{Part} %l%.%c</template>
      <template match="self::db:sect1">%l%.%c</template>
      <template match="self::db:sect2">%l%.%c</template>
      <template match="self::db:sect3">%l%.%c</template>
      <template match="self::db:sect4">%l%.%c</template>
      <template match="self::db:sect5">%l%.%c</template>
      <template match="self::db:section">%l%.%c</template>
      <template match="self::db:simplesect">%c</template>
      <template match="self::db:refsection">%c</template>
      <template match="self::db:refsect1">%c</template>
      <template match="self::db:refsect2">%c</template>
      <template match="self::db:refsect3">%c</template>
      <template match="self::db:abstract">%c</template>
      <template match="self::db:answer">%c</template>
      <template match="self::db:article">%c</template>
      <template match="self::db:authorblurb">%c</template>
      <template match="self::db:bibliodiv">%c</template>
      <template match="self::db:biblioentry">%c</template>
      <template match="self::db:bibliography">%c</template>
      <template match="self::db:bibliolist">%c</template>
      <template match="self::db:bibliomixed">%c</template>
      <template match="self::db:bibliomset">%c</template>
      <template match="self::db:biblioset">%c</template>
      <template match="self::db:blockquote">%c</template>
      <template match="self::db:book">%c</template>
      <template match="self::db:calloutlist">%c</template>
      <template match="self::db:caution">%c</template>
      <template match="self::db:colophon">%c</template>
      <template match="self::db:dedication">%c</template>
      <template match="self::db:equation">{Equation} %l%.%c</template>
      <template match="self::db:example">{Example} %l%.%c</template>
      <template match="self::db:figure">{Figure} %l%.%c</template>
      <template match="self::db:foil">%c</template>
      <template match="self::db:foilgroup">%c</template>
      <template match="self::db:formalpara">%c</template>
      <template match="self::db:glossary">%c</template>
      <template match="self::db:glossdiv">%c</template>
      <template match="self::db:glosslist">%c</template>
      <template match="self::db:glossentry">%c</template>
      <template match="self::db:important">%c</template>
      <template match="self::db:index">%c</template>
      <template match="self::db:indexdiv">%c</template>
      <template match="self::db:itemizedlist">%c</template>
      <template match="self::db:legalnotice">%c</template>
      <template match="self::db:listitem"/>
      <template match="self::db:lot">%c</template>
      <template match="self::db:msg">%c</template>
      <template match="self::db:msgexplan">%c</template>
      <template match="self::db:msgmain">%c</template>
      <template match="self::db:msgrel">%c</template>
      <template match="self::db:msgset">%c</template>
      <template match="self::db:msgsub">%c</template>
      <template match="self::db:note">%c</template>
      <template match="self::db:orderedlist">%c</template>
      <template match="self::db:partintro">%c</template>
      <template match="self::db:preface">%c</template>
      <template match="self::db:procedure">{Procedure} %l%.%c</template>
      <template match="self::db:productionset">%c</template>
      <template match="self::db:productionset.formal">{ProductionSet} %l</template>
      <template match="self::db:qandadiv">%c</template>
      <template match="self::db:qandaentry">%c</template>
      <template match="self::db:qandaset">%c</template>
      <template match="self::db:question">%c</template>
      <template match="self::db:refentry">%c</template>
      <template match="self::db:reference">%c</template>
      <template match="self::db:refsynopsisdiv">%c</template>
      <template match="self::db:refsynopsisdivinfo">%c</template>
      <template match="self::db:segmentedlist">%c</template>
      <template match="self::db:set">%c</template>
      <template match="self::db:setindex">%c</template>
      <template match="self::db:sidebar">%c</template>
      <template match="self::db:step">%c</template>
      <template match="self::db:table">{Table} %l%.%c</template>
      <template match="self::db:task">%c</template>
      <template match="self::db:tasksummary">%c</template>
      <template match="self::db:taskprerequisites">%c</template>
      <template match="self::db:taskrelated">%c</template>
      <template match="self::db:tip">%c</template>
      <template match="self::db:toc">%c</template>
      <template match="self::db:variablelist">%c</template>
      <template match="self::db:varlistentry"/>
      <template match="self::db:warning">%c</template>
      <template match="self::db:formalgroup[db:equation]">{Equation} %l%.%c</template>
      <template match="self::db:formalgroup[db:example]">{Example} %l%.%c</template>
      <template match="self::db:formalgroup[db:figure]">{Figure} %l%.%c</template>
      <template match="self::db:formalgroup[db:table]">{Table} %l%.%c</template>
      <template match="true()">%l%.%c</template>
   </group>
   <group name="subfigure-title">
      <template match="self::db:figure">{subfigure} %l%.%c</template>
      <template match="self::db:table">{subtable} %l%.%c</template>
      <template match="self::db:equation">{subequation} %l%.%c</template>
      <template match="self::db:example">{subexample} %l%.%c</template>
   </group>
   <group name="title-generated">
      <template match="self::db:abstract">{Abstract}</template>
      <template match="self::db:acknowledgements">{Acknowledgements}</template>
      <template match="self::db:bibliography">{Bibliography}</template>
      <template match="self::db:caution">{Caution}</template>
      <template match="self::db:danger">{Danger}</template>
      <template match="self::db:dedication">{Dedication}</template>
      <template match="self::db:glossary">{Glossary}</template>
      <template match="self::db:important">{Important}</template>
      <template match="self::db:index">{Index}</template>
      <template match="self::db:legalnotice">{LegalNotice}</template>
      <template match="self::db:note">{Note}</template>
      <template match="self::db:revhistory">{RevHistory}</template>
      <template match="self::db:setindex">{SetIndex}</template>
      <template match="self::db:tip">{Tip}</template>
      <template match="self::db:warning">{Warning}</template>
   </group>
   <group name="xref">
      <template match="self::db:section[ancestor::db:preface]">{sectioncalled} %c</template>
      <template match="self::db:sect1[ancestor::db:preface]">{sectioncalled} %c</template>
      <template match="self::db:sect2[ancestor::db:preface]">{sectioncalled} %c</template>
      <template match="self::db:sect3[ancestor::db:preface]">{sectioncalled} %c</template>
      <template match="self::db:sect4[ancestor::db:preface]">{sectioncalled} %c</template>
      <template match="self::db:sect5[ancestor::db:preface]">{sectioncalled} %c</template>
      <template match="self::db:danger">%c</template>
      <template match="self::db:production">%c</template>
      <template match="self::db:bibliolist">%c</template>
      <template match="self::db:glosslist">%c</template>
      <template match="self::db:abstract">%c</template>
      <template match="self::db:answer">{Answer} %l</template>
      <template match="self::db:appendix">%c</template>
      <template match="self::db:article">%c</template>
      <template match="self::db:authorblurb">%c</template>
      <template match="self::db:bibliodiv">%c</template>
      <template match="self::db:bibliography">%c</template>
      <template match="self::db:bibliomset">%c</template>
      <template match="self::db:biblioset">%c</template>
      <template match="self::db:blockquote">%c</template>
      <template match="self::db:book">%c</template>
      <template match="self::db:calloutlist">%c</template>
      <template match="self::db:caution">%c</template>
      <template match="self::db:chapter">%c</template>
      <template match="self::db:colophon">%c</template>
      <template match="self::db:constraintdef">%c</template>
      <template match="self::db:dedication">%c</template>
      <template match="self::db:equation">%c</template>
      <template match="self::db:example">%c</template>
      <template match="self::db:figure">%c</template>
      <template match="self::db:foil">%c</template>
      <template match="self::db:foilgroup">%c</template>
      <template match="self::db:formalpara">%c</template>
      <template match="self::db:glossary">%c</template>
      <template match="self::db:glossdiv">%c</template>
      <template match="self::db:important">%c</template>
      <template match="self::db:index">%c</template>
      <template match="self::db:indexdiv">%c</template>
      <template match="self::db:itemizedlist">%c</template>
      <template match="self::db:legalnotice">%c</template>
      <template match="self::db:lot">%c</template>
      <template match="self::db:msg">%c</template>
      <template match="self::db:msgexplan">%c</template>
      <template match="self::db:msgmain">%c</template>
      <template match="self::db:msgrel">%c</template>
      <template match="self::db:msgset">%c</template>
      <template match="self::db:msgsub">%c</template>
      <template match="self::db:note">%c</template>
      <template match="self::db:orderedlist">%c</template>
      <template match="self::db:part">%c</template>
      <template match="self::db:partintro">%c</template>
      <template match="self::db:preface">%c</template>
      <template match="self::db:procedure">%c</template>
      <template match="self::db:productionset">%c</template>
      <template match="self::db:qandadiv">%c</template>
      <template match="self::db:qandaentry">{Question} %l</template>
      <template match="self::db:qandaset">%c</template>
      <template match="self::db:question">{Question} %l</template>
      <template match="self::db:reference">%c</template>
      <template match="self::db:refsynopsisdiv">%c</template>
      <template match="self::db:segmentedlist">%c</template>
      <template match="self::db:set">%c</template>
      <template match="self::db:setindex">%c</template>
      <template match="self::db:sidebar">%c</template>
      <template match="self::db:table">%c</template>
      <template match="self::db:task">%c</template>
      <template match="self::db:tip">%c</template>
      <template match="self::db:toc">%c</template>
      <template match="self::db:variablelist">%c</template>
      <template match="self::db:warning">%c</template>
      <template match="self::db:olink.document.citation"> in %o</template>
      <template match="self::db:olink.page.citation"> (pagina %p)</template>
      <template match="self::db:page.citation"> [%p]</template>
      <template match="self::db:page">(pagina %p)</template>
      <template match="self::db:docname"> in %o</template>
      <template match="self::db:docnamelong"> nel documento dal titolo %o</template>
      <template match="self::db:pageabbrev">(p%.%p)</template>
      <template match="self::db:Page">Pagina %p</template>
      <template match="self::db:bridgehead">{sectioncalled} {startquote}%c{endquote}</template>
      <template match="self::db:refsection">{sectioncalled} {startquote}%c{endquote}</template>
      <template match="self::db:refsect1">{sectioncalled} {startquote}%c{endquote}</template>
      <template match="self::db:refsect2">{sectioncalled} {startquote}%c{endquote}</template>
      <template match="self::db:refsect3">{sectioncalled} {startquote}%c{endquote}</template>
      <template match="self::db:sect1">{sectioncalled} {startquote}%c{endquote}</template>
      <template match="self::db:sect2">{sectioncalled} {startquote}%c{endquote}</template>
      <template match="self::db:sect3">{sectioncalled} {startquote}%c{endquote}</template>
      <template match="self::db:sect4">{sectioncalled} {startquote}%c{endquote}</template>
      <template match="self::db:sect5">{sectioncalled} {startquote}%c{endquote}</template>
      <template match="self::db:section">{sectioncalled} {startquote}%c{endquote}</template>
      <template match="self::db:simplesect">{sectioncalled} {startquote}%c{endquote}</template>
      <template match="self::db:step">{step} %l</template>
      <template match="self::db:refnamediv">%c</template>
      <template match="true()">%l</template>
   </group>
   <group name="xref-number">
      <template match="self::db:answer">{Answer} %l</template>
      <template match="self::db:appendix">{Appendix} %l</template>
      <template match="self::db:bridgehead">{Section} %l</template>
      <template match="self::db:chapter">{Chapter} %l</template>
      <template match="self::db:equation">{Equation} %l</template>
      <template match="self::db:example">{Example} %l</template>
      <template match="self::db:figure">{Figure} %l</template>
      <template match="self::db:part">{Part} %l</template>
      <template match="self::db:procedure">{Procedure} %l</template>
      <template match="self::db:productionset">{ProductionSet} %l</template>
      <template match="self::db:qandadiv">{Qandadiv} %l</template>
      <template match="self::db:qandaentry">{Question} %l</template>
      <template match="self::db:question">{Question} %l</template>
      <template match="self::db:sect1">{Section} %l</template>
      <template match="self::db:sect2">{Section} %l</template>
      <template match="self::db:sect3">{Section} %l</template>
      <template match="self::db:sect4">{Section} %l</template>
      <template match="self::db:sect5">{Section} %l</template>
      <template match="self::db:section">{Section} %l</template>
      <template match="self::db:table">{Table} %l</template>
   </group>
   <group name="xref-number-and-title">
      <template match="self::db:appendix">{Appendix} %l, %c</template>
      <template match="self::db:bridgehead">{Section} %l, {startquote}%c{endquote}</template>
      <template match="self::db:chapter">{Chapter} %l, %c</template>
      <template match="self::db:equation">{Equation} %l, {startquote}%c{endquote}</template>
      <template match="self::db:example">{Example} %l, {startquote}%c{endquote}</template>
      <template match="self::db:figure">{Figure} %l, {startquote}%c{endquote}</template>
      <template match="self::db:part">{Part} %l, {startquote}%c{endquote}</template>
      <template match="self::db:procedure">{Procedure} %l, {startquote}%c{endquote}</template>
      <template match="self::db:productionset">{ProductionSet} %l, {startquote}%c{endquote}</template>
      <template match="self::db:qandadiv">{Qandadiv} %l, {startquote}%c{endquote}</template>
      <template match="self::db:refsect1">{sectioncalled} {startquote}%c{endquote}</template>
      <template match="self::db:refsect2">{sectioncalled} {startquote}%c{endquote}</template>
      <template match="self::db:refsect3">{sectioncalled} {startquote}%c{endquote}</template>
      <template match="self::db:refsection">{sectioncalled} {startquote}%c{endquote}</template>
      <template match="self::db:sect1">{Section} %l, {startquote}%c{endquote}</template>
      <template match="self::db:sect2">{Section} %l, {startquote}%c{endquote}</template>
      <template match="self::db:sect3">{Section} %l, {startquote}%c{endquote}</template>
      <template match="self::db:sect4">{Section} %l, {startquote}%c{endquote}</template>
      <template match="self::db:sect5">{Section} %l, {startquote}%c{endquote}</template>
      <template match="self::db:section">{Section} %l, {startquote}%c{endquote}</template>
      <template match="self::db:simplesect">{sectioncalled} {startquote}%c{endquote}</template>
      <template match="self::db:table">{Table} %l, {startquote}%c{endquote}</template>
      <template match="true()">%l%.%c</template>
   </group>
   <group name="see">
      <template match="self::db:glosssee">{GlossSee} %c.</template>
   </group>
   <list name="index-seealso">
      <items>({seealso} %c)</items>
      <items>({seealso} %c<repeat>, %c</repeat>)</items>
   </list>
   <list name="index-seeie">
      <items>({see} %c)</items>
      <items>({see} %c<repeat>, %c</repeat>)</items>
   </list>
   <list name="index-seealsoie">
      <items>({seealso} %c)</items>
      <items>({seealso} %c<repeat>, %c</repeat>)</items>
   </list>
   <list name="glossary-seealso">
      <items>{Seealso} %c.</items>
      <items>{Seealso} %c<repeat>, %c</repeat>.</items>
   </list>
   <list name="varlistentry">
      <items>%c</items>
      <items>%c<repeat>, %c</repeat>
      </items>
   </list>
   <list name="_default">
      <items>%c</items>
      <items>%c {and} %c</items>
      <items>%c<repeat>, %c</repeat>, {and} %c</items>
   </list>
   <letters>
      <l i="-1"/>
      <l i="0">Simboli</l>
      <l i="10">A</l>
      <l i="10">a</l>
      <l i="10">À</l>
      <l i="10">à</l>
      <l i="10">Á</l>
      <l i="10">á</l>
      <l i="10">Â</l>
      <l i="10">â</l>
      <l i="10">Ã</l>
      <l i="10">ã</l>
      <l i="10">Ä</l>
      <l i="10">ä</l>
      <l i="10">Å</l>
      <l i="10">å</l>
      <l i="10">Ā</l>
      <l i="10">ā</l>
      <l i="10">Ă</l>
      <l i="10">ă</l>
      <l i="10">Ą</l>
      <l i="10">ą</l>
      <l i="10">Ǎ</l>
      <l i="10">ǎ</l>
      <l i="10">Ǟ</l>
      <l i="10">ǟ</l>
      <l i="10">Ǡ</l>
      <l i="10">ǡ</l>
      <l i="10">Ǻ</l>
      <l i="10">ǻ</l>
      <l i="10">Ȁ</l>
      <l i="10">ȁ</l>
      <l i="10">Ȃ</l>
      <l i="10">ȃ</l>
      <l i="10">Ȧ</l>
      <l i="10">ȧ</l>
      <l i="10">Ḁ</l>
      <l i="10">ḁ</l>
      <l i="10">ẚ</l>
      <l i="10">Ạ</l>
      <l i="10">ạ</l>
      <l i="10">Ả</l>
      <l i="10">ả</l>
      <l i="10">Ấ</l>
      <l i="10">ấ</l>
      <l i="10">Ầ</l>
      <l i="10">ầ</l>
      <l i="10">Ẩ</l>
      <l i="10">ẩ</l>
      <l i="10">Ẫ</l>
      <l i="10">ẫ</l>
      <l i="10">Ậ</l>
      <l i="10">ậ</l>
      <l i="10">Ắ</l>
      <l i="10">ắ</l>
      <l i="10">Ằ</l>
      <l i="10">ằ</l>
      <l i="10">Ẳ</l>
      <l i="10">ẳ</l>
      <l i="10">Ẵ</l>
      <l i="10">ẵ</l>
      <l i="10">Ặ</l>
      <l i="10">ặ</l>
      <l i="20">B</l>
      <l i="20">b</l>
      <l i="20">ƀ</l>
      <l i="20">Ɓ</l>
      <l i="20">ɓ</l>
      <l i="20">Ƃ</l>
      <l i="20">ƃ</l>
      <l i="20">Ḃ</l>
      <l i="20">ḃ</l>
      <l i="20">Ḅ</l>
      <l i="20">ḅ</l>
      <l i="20">Ḇ</l>
      <l i="20">ḇ</l>
      <l i="30">C</l>
      <l i="30">c</l>
      <l i="30">Ç</l>
      <l i="30">ç</l>
      <l i="30">Ć</l>
      <l i="30">ć</l>
      <l i="30">Ĉ</l>
      <l i="30">ĉ</l>
      <l i="30">Ċ</l>
      <l i="30">ċ</l>
      <l i="30">Č</l>
      <l i="30">č</l>
      <l i="30">Ƈ</l>
      <l i="30">ƈ</l>
      <l i="30">ɕ</l>
      <l i="30">Ḉ</l>
      <l i="30">ḉ</l>
      <l i="40">D</l>
      <l i="40">d</l>
      <l i="40">Ď</l>
      <l i="40">ď</l>
      <l i="40">Đ</l>
      <l i="40">đ</l>
      <l i="40">Ɗ</l>
      <l i="40">ɗ</l>
      <l i="40">Ƌ</l>
      <l i="40">ƌ</l>
      <l i="40">ǅ</l>
      <l i="40">ǲ</l>
      <l i="40">ȡ</l>
      <l i="40">ɖ</l>
      <l i="40">Ḋ</l>
      <l i="40">ḋ</l>
      <l i="40">Ḍ</l>
      <l i="40">ḍ</l>
      <l i="40">Ḏ</l>
      <l i="40">ḏ</l>
      <l i="40">Ḑ</l>
      <l i="40">ḑ</l>
      <l i="40">Ḓ</l>
      <l i="40">ḓ</l>
      <l i="50">E</l>
      <l i="50">e</l>
      <l i="50">È</l>
      <l i="50">è</l>
      <l i="50">É</l>
      <l i="50">é</l>
      <l i="50">Ê</l>
      <l i="50">ê</l>
      <l i="50">Ë</l>
      <l i="50">ë</l>
      <l i="50">Ē</l>
      <l i="50">ē</l>
      <l i="50">Ĕ</l>
      <l i="50">ĕ</l>
      <l i="50">Ė</l>
      <l i="50">ė</l>
      <l i="50">Ę</l>
      <l i="50">ę</l>
      <l i="50">Ě</l>
      <l i="50">ě</l>
      <l i="50">Ȅ</l>
      <l i="50">ȅ</l>
      <l i="50">Ȇ</l>
      <l i="50">ȇ</l>
      <l i="50">Ȩ</l>
      <l i="50">ȩ</l>
      <l i="50">Ḕ</l>
      <l i="50">ḕ</l>
      <l i="50">Ḗ</l>
      <l i="50">ḗ</l>
      <l i="50">Ḙ</l>
      <l i="50">ḙ</l>
      <l i="50">Ḛ</l>
      <l i="50">ḛ</l>
      <l i="50">Ḝ</l>
      <l i="50">ḝ</l>
      <l i="50">Ẹ</l>
      <l i="50">ẹ</l>
      <l i="50">Ẻ</l>
      <l i="50">ẻ</l>
      <l i="50">Ẽ</l>
      <l i="50">ẽ</l>
      <l i="50">Ế</l>
      <l i="50">ế</l>
      <l i="50">Ề</l>
      <l i="50">ề</l>
      <l i="50">Ể</l>
      <l i="50">ể</l>
      <l i="50">Ễ</l>
      <l i="50">ễ</l>
      <l i="50">Ệ</l>
      <l i="50">ệ</l>
      <l i="60">F</l>
      <l i="60">f</l>
      <l i="60">Ƒ</l>
      <l i="60">ƒ</l>
      <l i="60">Ḟ</l>
      <l i="60">ḟ</l>
      <l i="70">G</l>
      <l i="70">g</l>
      <l i="70">Ĝ</l>
      <l i="70">ĝ</l>
      <l i="70">Ğ</l>
      <l i="70">ğ</l>
      <l i="70">Ġ</l>
      <l i="70">ġ</l>
      <l i="70">Ģ</l>
      <l i="70">ģ</l>
      <l i="70">Ɠ</l>
      <l i="70">ɠ</l>
      <l i="70">Ǥ</l>
      <l i="70">ǥ</l>
      <l i="70">Ǧ</l>
      <l i="70">ǧ</l>
      <l i="70">Ǵ</l>
      <l i="70">ǵ</l>
      <l i="70">Ḡ</l>
      <l i="70">ḡ</l>
      <l i="80">H</l>
      <l i="80">h</l>
      <l i="80">Ĥ</l>
      <l i="80">ĥ</l>
      <l i="80">Ħ</l>
      <l i="80">ħ</l>
      <l i="80">Ȟ</l>
      <l i="80">ȟ</l>
      <l i="80">ɦ</l>
      <l i="80">Ḣ</l>
      <l i="80">ḣ</l>
      <l i="80">Ḥ</l>
      <l i="80">ḥ</l>
      <l i="80">Ḧ</l>
      <l i="80">ḧ</l>
      <l i="80">Ḩ</l>
      <l i="80">ḩ</l>
      <l i="80">Ḫ</l>
      <l i="80">ḫ</l>
      <l i="80">ẖ</l>
      <l i="90">I</l>
      <l i="90">i</l>
      <l i="90">Ì</l>
      <l i="90">ì</l>
      <l i="90">Í</l>
      <l i="90">í</l>
      <l i="90">Î</l>
      <l i="90">î</l>
      <l i="90">Ï</l>
      <l i="90">ï</l>
      <l i="90">Ĩ</l>
      <l i="90">ĩ</l>
      <l i="90">Ī</l>
      <l i="90">ī</l>
      <l i="90">Ĭ</l>
      <l i="90">ĭ</l>
      <l i="90">Į</l>
      <l i="90">į</l>
      <l i="90">İ</l>
      <l i="90">Ɨ</l>
      <l i="90">ɨ</l>
      <l i="90">Ǐ</l>
      <l i="90">ǐ</l>
      <l i="90">Ȉ</l>
      <l i="90">ȉ</l>
      <l i="90">Ȋ</l>
      <l i="90">ȋ</l>
      <l i="90">Ḭ</l>
      <l i="90">ḭ</l>
      <l i="90">Ḯ</l>
      <l i="90">ḯ</l>
      <l i="90">Ỉ</l>
      <l i="90">ỉ</l>
      <l i="90">Ị</l>
      <l i="90">ị</l>
      <l i="100">J</l>
      <l i="100">j</l>
      <l i="100">Ĵ</l>
      <l i="100">ĵ</l>
      <l i="100">ǰ</l>
      <l i="100">ʝ</l>
      <l i="110">K</l>
      <l i="110">k</l>
      <l i="110">Ķ</l>
      <l i="110">ķ</l>
      <l i="110">Ƙ</l>
      <l i="110">ƙ</l>
      <l i="110">Ǩ</l>
      <l i="110">ǩ</l>
      <l i="110">Ḱ</l>
      <l i="110">ḱ</l>
      <l i="110">Ḳ</l>
      <l i="110">ḳ</l>
      <l i="110">Ḵ</l>
      <l i="110">ḵ</l>
      <l i="120">L</l>
      <l i="120">l</l>
      <l i="120">Ĺ</l>
      <l i="120">ĺ</l>
      <l i="120">Ļ</l>
      <l i="120">ļ</l>
      <l i="120">Ľ</l>
      <l i="120">ľ</l>
      <l i="120">Ŀ</l>
      <l i="120">ŀ</l>
      <l i="120">Ł</l>
      <l i="120">ł</l>
      <l i="120">ƚ</l>
      <l i="120">ǈ</l>
      <l i="120">ȴ</l>
      <l i="120">ɫ</l>
      <l i="120">ɬ</l>
      <l i="120">ɭ</l>
      <l i="120">Ḷ</l>
      <l i="120">ḷ</l>
      <l i="120">Ḹ</l>
      <l i="120">ḹ</l>
      <l i="120">Ḻ</l>
      <l i="120">ḻ</l>
      <l i="120">Ḽ</l>
      <l i="120">ḽ</l>
      <l i="130">M</l>
      <l i="130">m</l>
      <l i="130">ɱ</l>
      <l i="130">Ḿ</l>
      <l i="130">ḿ</l>
      <l i="130">Ṁ</l>
      <l i="130">ṁ</l>
      <l i="130">Ṃ</l>
      <l i="130">ṃ</l>
      <l i="140">N</l>
      <l i="140">n</l>
      <l i="140">Ñ</l>
      <l i="140">ñ</l>
      <l i="140">Ń</l>
      <l i="140">ń</l>
      <l i="140">Ņ</l>
      <l i="140">ņ</l>
      <l i="140">Ň</l>
      <l i="140">ň</l>
      <l i="140">Ɲ</l>
      <l i="140">ɲ</l>
      <l i="140">ƞ</l>
      <l i="140">Ƞ</l>
      <l i="140">ǋ</l>
      <l i="140">Ǹ</l>
      <l i="140">ǹ</l>
      <l i="140">ȵ</l>
      <l i="140">ɳ</l>
      <l i="140">Ṅ</l>
      <l i="140">ṅ</l>
      <l i="140">Ṇ</l>
      <l i="140">ṇ</l>
      <l i="140">Ṉ</l>
      <l i="140">ṉ</l>
      <l i="140">Ṋ</l>
      <l i="140">ṋ</l>
      <l i="150">O</l>
      <l i="150">o</l>
      <l i="150">Ò</l>
      <l i="150">ò</l>
      <l i="150">Ó</l>
      <l i="150">ó</l>
      <l i="150">Ô</l>
      <l i="150">ô</l>
      <l i="150">Õ</l>
      <l i="150">õ</l>
      <l i="150">Ö</l>
      <l i="150">ö</l>
      <l i="150">Ø</l>
      <l i="150">ø</l>
      <l i="150">Ō</l>
      <l i="150">ō</l>
      <l i="150">Ŏ</l>
      <l i="150">ŏ</l>
      <l i="150">Ő</l>
      <l i="150">ő</l>
      <l i="150">Ɵ</l>
      <l i="150">Ơ</l>
      <l i="150">ơ</l>
      <l i="150">Ǒ</l>
      <l i="150">ǒ</l>
      <l i="150">Ǫ</l>
      <l i="150">ǫ</l>
      <l i="150">Ǭ</l>
      <l i="150">ǭ</l>
      <l i="150">Ǿ</l>
      <l i="150">ǿ</l>
      <l i="150">Ȍ</l>
      <l i="150">ȍ</l>
      <l i="150">Ȏ</l>
      <l i="150">ȏ</l>
      <l i="150">Ȫ</l>
      <l i="150">ȫ</l>
      <l i="150">Ȭ</l>
      <l i="150">ȭ</l>
      <l i="150">Ȯ</l>
      <l i="150">ȯ</l>
      <l i="150">Ȱ</l>
      <l i="150">ȱ</l>
      <l i="150">Ṍ</l>
      <l i="150">ṍ</l>
      <l i="150">Ṏ</l>
      <l i="150">ṏ</l>
      <l i="150">Ṑ</l>
      <l i="150">ṑ</l>
      <l i="150">Ṓ</l>
      <l i="150">ṓ</l>
      <l i="150">Ọ</l>
      <l i="150">ọ</l>
      <l i="150">Ỏ</l>
      <l i="150">ỏ</l>
      <l i="150">Ố</l>
      <l i="150">ố</l>
      <l i="150">Ồ</l>
      <l i="150">ồ</l>
      <l i="150">Ổ</l>
      <l i="150">ổ</l>
      <l i="150">Ỗ</l>
      <l i="150">ỗ</l>
      <l i="150">Ộ</l>
      <l i="150">ộ</l>
      <l i="150">Ớ</l>
      <l i="150">ớ</l>
      <l i="150">Ờ</l>
      <l i="150">ờ</l>
      <l i="150">Ở</l>
      <l i="150">ở</l>
      <l i="150">Ỡ</l>
      <l i="150">ỡ</l>
      <l i="150">Ợ</l>
      <l i="150">ợ</l>
      <l i="160">P</l>
      <l i="160">p</l>
      <l i="160">Ƥ</l>
      <l i="160">ƥ</l>
      <l i="160">Ṕ</l>
      <l i="160">ṕ</l>
      <l i="160">Ṗ</l>
      <l i="160">ṗ</l>
      <l i="170">Q</l>
      <l i="170">q</l>
      <l i="170">ʠ</l>
      <l i="180">R</l>
      <l i="180">r</l>
      <l i="180">Ŕ</l>
      <l i="180">ŕ</l>
      <l i="180">Ŗ</l>
      <l i="180">ŗ</l>
      <l i="180">Ř</l>
      <l i="180">ř</l>
      <l i="180">Ȑ</l>
      <l i="180">ȑ</l>
      <l i="180">Ȓ</l>
      <l i="180">ȓ</l>
      <l i="180">ɼ</l>
      <l i="180">ɽ</l>
      <l i="180">ɾ</l>
      <l i="180">Ṙ</l>
      <l i="180">ṙ</l>
      <l i="180">Ṛ</l>
      <l i="180">ṛ</l>
      <l i="180">Ṝ</l>
      <l i="180">ṝ</l>
      <l i="180">Ṟ</l>
      <l i="180">ṟ</l>
      <l i="190">S</l>
      <l i="190">s</l>
      <l i="190">Ś</l>
      <l i="190">ś</l>
      <l i="190">Ŝ</l>
      <l i="190">ŝ</l>
      <l i="190">Ş</l>
      <l i="190">ş</l>
      <l i="190">Š</l>
      <l i="190">š</l>
      <l i="190">Ș</l>
      <l i="190">ș</l>
      <l i="190">ʂ</l>
      <l i="190">Ṡ</l>
      <l i="190">ṡ</l>
      <l i="190">Ṣ</l>
      <l i="190">ṣ</l>
      <l i="190">Ṥ</l>
      <l i="190">ṥ</l>
      <l i="190">Ṧ</l>
      <l i="190">ṧ</l>
      <l i="190">Ṩ</l>
      <l i="190">ṩ</l>
      <l i="200">T</l>
      <l i="200">t</l>
      <l i="200">Ţ</l>
      <l i="200">ţ</l>
      <l i="200">Ť</l>
      <l i="200">ť</l>
      <l i="200">Ŧ</l>
      <l i="200">ŧ</l>
      <l i="200">ƫ</l>
      <l i="200">Ƭ</l>
      <l i="200">ƭ</l>
      <l i="200">Ʈ</l>
      <l i="200">ʈ</l>
      <l i="200">Ț</l>
      <l i="200">ț</l>
      <l i="200">ȶ</l>
      <l i="200">Ṫ</l>
      <l i="200">ṫ</l>
      <l i="200">Ṭ</l>
      <l i="200">ṭ</l>
      <l i="200">Ṯ</l>
      <l i="200">ṯ</l>
      <l i="200">Ṱ</l>
      <l i="200">ṱ</l>
      <l i="200">ẗ</l>
      <l i="210">U</l>
      <l i="210">u</l>
      <l i="210">Ù</l>
      <l i="210">ù</l>
      <l i="210">Ú</l>
      <l i="210">ú</l>
      <l i="210">Û</l>
      <l i="210">û</l>
      <l i="210">Ü</l>
      <l i="210">ü</l>
      <l i="210">Ũ</l>
      <l i="210">ũ</l>
      <l i="210">Ū</l>
      <l i="210">ū</l>
      <l i="210">Ŭ</l>
      <l i="210">ŭ</l>
      <l i="210">Ů</l>
      <l i="210">ů</l>
      <l i="210">Ű</l>
      <l i="210">ű</l>
      <l i="210">Ų</l>
      <l i="210">ų</l>
      <l i="210">Ư</l>
      <l i="210">ư</l>
      <l i="210">Ǔ</l>
      <l i="210">ǔ</l>
      <l i="210">Ǖ</l>
      <l i="210">ǖ</l>
      <l i="210">Ǘ</l>
      <l i="210">ǘ</l>
      <l i="210">Ǚ</l>
      <l i="210">ǚ</l>
      <l i="210">Ǜ</l>
      <l i="210">ǜ</l>
      <l i="210">Ȕ</l>
      <l i="210">ȕ</l>
      <l i="210">Ȗ</l>
      <l i="210">ȗ</l>
      <l i="210">Ṳ</l>
      <l i="210">ṳ</l>
      <l i="210">Ṵ</l>
      <l i="210">ṵ</l>
      <l i="210">Ṷ</l>
      <l i="210">ṷ</l>
      <l i="210">Ṹ</l>
      <l i="210">ṹ</l>
      <l i="210">Ṻ</l>
      <l i="210">ṻ</l>
      <l i="210">Ụ</l>
      <l i="210">ụ</l>
      <l i="210">Ủ</l>
      <l i="210">ủ</l>
      <l i="210">Ứ</l>
      <l i="210">ứ</l>
      <l i="210">Ừ</l>
      <l i="210">ừ</l>
      <l i="210">Ử</l>
      <l i="210">ử</l>
      <l i="210">Ữ</l>
      <l i="210">ữ</l>
      <l i="210">Ự</l>
      <l i="210">ự</l>
      <l i="220">V</l>
      <l i="220">v</l>
      <l i="220">Ʋ</l>
      <l i="220">ʋ</l>
      <l i="220">Ṽ</l>
      <l i="220">ṽ</l>
      <l i="220">Ṿ</l>
      <l i="220">ṿ</l>
      <l i="230">W</l>
      <l i="230">w</l>
      <l i="230">Ŵ</l>
      <l i="230">ŵ</l>
      <l i="230">Ẁ</l>
      <l i="230">ẁ</l>
      <l i="230">Ẃ</l>
      <l i="230">ẃ</l>
      <l i="230">Ẅ</l>
      <l i="230">ẅ</l>
      <l i="230">Ẇ</l>
      <l i="230">ẇ</l>
      <l i="230">Ẉ</l>
      <l i="230">ẉ</l>
      <l i="230">ẘ</l>
      <l i="240">X</l>
      <l i="240">x</l>
      <l i="240">Ẋ</l>
      <l i="240">ẋ</l>
      <l i="240">Ẍ</l>
      <l i="240">ẍ</l>
      <l i="250">Y</l>
      <l i="250">y</l>
      <l i="250">Ý</l>
      <l i="250">ý</l>
      <l i="250">ÿ</l>
      <l i="250">Ÿ</l>
      <l i="250">Ŷ</l>
      <l i="250">ŷ</l>
      <l i="250">Ƴ</l>
      <l i="250">ƴ</l>
      <l i="250">Ȳ</l>
      <l i="250">ȳ</l>
      <l i="250">Ẏ</l>
      <l i="250">ẏ</l>
      <l i="250">ẙ</l>
      <l i="250">Ỳ</l>
      <l i="250">ỳ</l>
      <l i="250">Ỵ</l>
      <l i="250">ỵ</l>
      <l i="250">Ỷ</l>
      <l i="250">ỷ</l>
      <l i="250">Ỹ</l>
      <l i="250">ỹ</l>
      <l i="260">Z</l>
      <l i="260">z</l>
      <l i="260">Ź</l>
      <l i="260">ź</l>
      <l i="260">Ż</l>
      <l i="260">ż</l>
      <l i="260">Ž</l>
      <l i="260">ž</l>
      <l i="260">Ƶ</l>
      <l i="260">ƶ</l>
      <l i="260">Ȥ</l>
      <l i="260">ȥ</l>
      <l i="260">ʐ</l>
      <l i="260">ʑ</l>
      <l i="260">Ẑ</l>
      <l i="260">ẑ</l>
      <l i="260">Ẓ</l>
      <l i="260">ẓ</l>
      <l i="260">Ẕ</l>
      <l i="260">ẕ</l>
   </letters>
</locale>
